{"data":[{"apartName":"명보2차아파트주민자치회","zipCode":"25801","convY":37.4961362,"address":"강원특별자치도 동해시 효가동 248 동해명보2차아파트","landNumber":"248","convX":129.1087263,"dongmyun":"효가동","apartCode":"A10023015","lawdCd":"51170","doroJuso":"강원특별자치도 동해시 효가로 10-2"},{"apartName":"천곡주공3차아파트","zipCode":"25772","convY":37.5193233,"address":"강원특별자치도 동해시 천곡동 306 동해천곡주공3차아파트","landNumber":"306","convX":129.1096385,"dongmyun":"천곡동","apartCode":"A10023334","lawdCd":"51170","doroJuso":"강원특별자치도 동해시 동굴로 61-19"},{"apartName":"동해석미아데나더퍼스트","zipCode":"25819","convY":37.4768874,"address":"강원특별자치도 동해시 이도동 757 동해 석미아데나 더퍼스트","landNumber":"757","convX":129.1103395,"dongmyun":"이도동","apartCode":"A10023736","lawdCd":"51170","doroJuso":"강원특별자치도 동해시 동해대로 4835"},{"apartName":"이안동해센트럴아파트","zipCode":"25758","convY":37.5264475,"address":"강원특별자치도 동해시 천곡동 788 이안 동해 센트럴","landNumber":"788","convX":129.1061493,"dongmyun":"천곡동","apartCode":"A10023962","lawdCd":"51170","doroJuso":"강원특별자치도 동해시 천곡로 5"},{"apartName":"아델리움 희담재","zipCode":"25785","convY":37.4950537,"address":"강원특별자치도 동해시 효가동 488 아델리움 희담재","landNumber":"488","convX":129.1142358,"dongmyun":"효가동","apartCode":"A10024319","lawdCd":"51170","doroJuso":"강원특별자치도 동해시 효가1로 58"},{"apartName":"동해천곡금호어울림라포레","zipCode":"25750","convY":37.5235573,"address":"강원특별자치도 동해시 천곡동 1111 천곡 금호어울림 라포레","landNumber":"1111","convX":129.1002736,"dongmyun":"천곡동","apartCode":"A10024855","lawdCd":"51170","doroJuso":"강원특별자치도 동해시 항골길 65"},{"apartName":"시영3차아파트","zipCode":"25775","convY":37.5161217,"address":"강원특별자치도 동해시 천곡동 1004-1 시영3차아파트","landNumber":"1004-1","convX":129.1073145,"dongmyun":"천곡동","apartCode":"A10024865","lawdCd":"51170","doroJuso":"강원특별자치도 동해시 동굴로 26"},{"apartName":"e편한세상동해아파트","zipCode":"25814","convY":37.4793566,"address":"강원특별자치도 동해시 북평동 327 e편한세상 동해","landNumber":"327","convX":129.1219629,"dongmyun":"북평동","apartCode":"A10024988","lawdCd":"51170","doroJuso":"강원특별자치도 동해시 단봉길 39"},{"apartName":"동해 이도 코아루 더 스카이","zipCode":"25819","convY":37.4770102,"address":"강원특별자치도 동해시 이도동 753 동해 이도 코아루 더스카이","landNumber":"753","convX":129.1121589,"dongmyun":"이도동","apartCode":"A10025030","lawdCd":"51170","doroJuso":"강원특별자치도 동해시 동해대로 4833"},{"apartName":"동해 ES아뜨리움아파트","zipCode":"25750","convY":37.5268366,"address":"강원특별자치도 동해시 천곡동 1105 ES아뜨리움아파트","landNumber":"1105","convX":129.0997953,"dongmyun":"천곡동","apartCode":"A10025141","lawdCd":"51170","doroJuso":"강원특별자치도 동해시 평릉길 21-1"},{"apartName":"북삼2차웰메이드타운","zipCode":"25806","convY":37.4906722,"address":"강원특별자치도 동해시 동회동 457 북삼2차 웰메이드타운","landNumber":"457","convX":129.1048245,"dongmyun":"동회동","apartCode":"A10025565","lawdCd":"51170","doroJuso":"강원특별자치도 동해시 효자로 636-2"},{"apartName":"동해 KD아람채아파트","zipCode":"25724","convY":37.5483013,"address":"강원특별자치도 동해시 발한동 802 동해 KD아람채 아파트","landNumber":"802","convX":129.1006577,"dongmyun":"발한동","apartCode":"A10025751","lawdCd":"51170","doroJuso":"강원특별자치도 동해시 지리골길 33"},{"apartName":"현대썬앤빌 동해파크힐","zipCode":"25724","convY":37.5478591,"address":"강원특별자치도 동해시 발한동 801 현대비에스앤씨 현대썬앤빌 동해파크힐","landNumber":"801","convX":129.1018008,"dongmyun":"발한동","apartCode":"A10025810","lawdCd":"51170","doroJuso":"강원특별자치도 동해시 지리골길 31"},{"apartName":"동해 아이파크아파트","zipCode":"25818","convY":37.4768748,"address":"강원특별자치도 동해시 이도동 751 동해아이파크","landNumber":"751","convX":129.1084857,"dongmyun":"이도동","apartCode":"A10025928","lawdCd":"51170","doroJuso":"강원특별자치도 동해시 배골길 32-4"},{"apartName":"북삼하우스디아파트","zipCode":"25806","convY":37.4897848,"address":"강원특별자치도 동해시 동회동 451 북삼하우스디아파트","landNumber":"451","convX":129.106196,"dongmyun":"동회동","apartCode":"A10026210","lawdCd":"51170","doroJuso":"강원특별자치도 동해시 효자남길 33-20"},{"apartName":"동해북평석미모닝파크","zipCode":"25814","convY":37.4790896,"address":"강원특별자치도 동해시 북평동 324 동해북평석미모닝파크","landNumber":"324","convX":129.1202567,"dongmyun":"북평동","apartCode":"A10026612","lawdCd":"51170","doroJuso":"강원특별자치도 동해시 단봉길 40"},{"apartName":"천곡한양수자인","zipCode":"25747","convY":37.5285204,"address":"강원특별자치도 동해시 천곡동 1103 천곡 한양수자인","landNumber":"1103","convX":129.0993434,"dongmyun":"천곡동","apartCode":"A10027258","lawdCd":"51170","doroJuso":"강원특별자치도 동해시 평릉1길 37-1"},{"apartName":"동해발한석미모닝파크","zipCode":"25713","convY":37.556837,"address":"강원특별자치도 동해시 발한동 778 동해발한석미모닝파크","landNumber":"778","convX":129.1022501,"dongmyun":"발한동","apartCode":"A10027958","lawdCd":"51170","doroJuso":"강원특별자치도 동해시 해안로 635-5"},{"apartName":"동해푸르지오아파트","zipCode":"25748","convY":37.5295631,"address":"강원특별자치도 동해시 평릉동 293 동해푸르지오","landNumber":"293","convX":129.0997143,"dongmyun":"평릉동","apartCode":"A24002001","lawdCd":"51170","doroJuso":"강원특별자치도 동해시 평릉1길 39"},{"apartName":"유존아파트","zipCode":"25735","convY":37.5378572,"address":"강원특별자치도 동해시 부곡동 111-1 유존아파트","landNumber":"111-1","convX":129.105939,"dongmyun":"부곡동","apartCode":"A24003001","lawdCd":"51170","doroJuso":"강원특별자치도 동해시 부곡2길 26-1"},{"apartName":"일정골든타워","zipCode":"25730","convY":37.541107,"address":"강원특별자치도 동해시 부곡동 5-82 일정골든타워","landNumber":"5-82","convX":129.1089262,"dongmyun":"부곡동","apartCode":"A24003003","lawdCd":"51170","doroJuso":"강원특별자치도 동해시 해안로 449"},{"apartName":"묵호LH아파트","zipCode":"25710","convY":37.5598822,"address":"강원특별자치도 동해시 묵호진동 110 묵호주공아파트","landNumber":"110","convX":129.1134684,"dongmyun":"묵호진동","apartCode":"A24005001","lawdCd":"51170","doroJuso":"강원특별자치도 동해시 해맞이길 215"},{"apartName":"동아더프라임2단지","zipCode":"25801","convY":37.4986606,"address":"강원특별자치도 동해시 효가동 481 동아 더 프라임 아파트","landNumber":"481","convX":129.1076051,"dongmyun":"효가동","apartCode":"A24016001","lawdCd":"51170","doroJuso":"강원특별자치도 동해시 양지길 20-1"},{"apartName":"동아더프라임 1단지","zipCode":"25801","convY":37.4995703,"address":"강원특별자치도 동해시 효가동 480 동아 더 프라임 아파트","landNumber":"480","convX":129.1067778,"dongmyun":"효가동","apartCode":"A24016002","lawdCd":"51170","doroJuso":"강원특별자치도 동해시 양지길 20-2"},{"apartName":"동회동현대코아루아파트","zipCode":"25807","convY":37.4873843,"address":"강원특별자치도 동해시 동회동 442 대동아파트, 동회동 현대아파트","landNumber":"442","convX":129.1059478,"dongmyun":"동회동","apartCode":"A24018003","lawdCd":"51170","doroJuso":"강원특별자치도 동해시 청운1길 29"},{"apartName":"대동아파트","zipCode":"25807","convY":37.4873843,"address":"강원특별자치도 동해시 동회동 442 대동아파트, 동회동 현대아파트","landNumber":"442","convX":129.1059478,"dongmyun":"동회동","apartCode":"A24018004","lawdCd":"51170","doroJuso":"강원특별자치도 동해시 청운1길 29"},{"apartName":"동해쇄운부영아파트","zipCode":"25809","convY":37.4853581,"address":"강원특별자치도 동해시 쇄운동 8 부영아파트","landNumber":"8","convX":129.1066513,"dongmyun":"쇄운동","apartCode":"A24019001","lawdCd":"51170","doroJuso":"강원특별자치도 동해시 청운1길 30"},{"apartName":"현진","zipCode":"25792","convY":37.4819256,"address":"강원특별자치도 동해시 구미동 521 현진에버빌","landNumber":"521","convX":129.130019,"dongmyun":"구미동","apartCode":"A24021001","lawdCd":"51170","doroJuso":"강원특별자치도 동해시 구미4길 1"},{"apartName":"동해강변","zipCode":"25818","convY":37.4812035,"address":"강원특별자치도 동해시 이도동 302-6 강변아파트","landNumber":"302-6","convX":129.1097306,"dongmyun":"이도동","apartCode":"A24029001","lawdCd":"51170","doroJuso":"강원특별자치도 동해시 전천로 175-24"},{"apartName":"이도현대","zipCode":"25819","convY":37.4794266,"address":"강원특별자치도 동해시 이도동 172 이도동현대아파트","landNumber":"172","convX":129.1114737,"dongmyun":"이도동","apartCode":"A24029002","lawdCd":"51170","doroJuso":"강원특별자치도 동해시 이원길 180"},{"apartName":"이도2주공","zipCode":"25819","convY":37.4783401,"address":"강원특별자치도 동해시 이도동 155 이도주공아파트","landNumber":"155","convX":129.1120595,"dongmyun":"이도동","apartCode":"A24029003","lawdCd":"51170","doroJuso":"강원특별자치도 동해시 이원길 180-2"},{"apartName":"이도1주공아파트","zipCode":"25819","convY":37.4783401,"address":"강원특별자치도 동해시 이도동 155 이도주공아파트","landNumber":"155","convX":129.1120595,"dongmyun":"이도동","apartCode":"A24029004","lawdCd":"51170","doroJuso":"강원특별자치도 동해시 이원길 180-2"},{"apartName":"천곡동아아파트","zipCode":"25761","convY":37.5220994,"address":"강원특별자치도 동해시 천곡동 1078-8 동아아파트","landNumber":"1078-8","convX":129.1119405,"dongmyun":"천곡동","apartCode":"A24070201","lawdCd":"51170","doroJuso":"강원특별자치도 동해시 천곡로 56-5"},{"apartName":"천곡LH5차아파트","zipCode":"25774","convY":37.5161333,"address":"강원특별자치도 동해시 천곡동 1098 동해천곡주공5차아파트","landNumber":"1098","convX":129.1054,"dongmyun":"천곡동","apartCode":"A24070202","lawdCd":"51170","doroJuso":"강원특별자치도 동해시 동굴로 15"},{"apartName":"동해엘리시아아파트","zipCode":"25739","convY":37.532325,"address":"강원특별자치도 동해시 평릉동 450 동해엘리시아아파트","landNumber":"450","convX":129.1117248,"dongmyun":"평릉동","apartCode":"A24071101","lawdCd":"51170","doroJuso":"강원특별자치도 동해시 평원로 107"},{"apartName":"하나리움아파트","zipCode":"25739","convY":37.5330691,"address":"강원특별자치도 동해시 평릉동 449 동해하나리움아파트","landNumber":"449","convX":129.1115378,"dongmyun":"평릉동","apartCode":"A24071102","lawdCd":"51170","doroJuso":"강원특별자치도 동해시 평원로 115"},{"apartName":"동해해안부영","zipCode":"25737","convY":37.5333552,"address":"강원특별자치도 동해시 평릉동 448 동해해안사랑으로부영","landNumber":"448","convX":129.1136712,"dongmyun":"평릉동","apartCode":"A24071103","lawdCd":"51170","doroJuso":"강원특별자치도 동해시 평원로 110"},{"apartName":"동해코아루디오션","zipCode":"25752","convY":37.5320853,"address":"강원특별자치도 동해시 평릉동 456 코아루디오션","landNumber":"456","convX":129.1148644,"dongmyun":"평릉동","apartCode":"A24071104","lawdCd":"51170","doroJuso":"강원특별자치도 동해시 평원로 100"},{"apartName":"동해송정LH아파트","zipCode":"25785","convY":37.4940468,"address":"강원특별자치도 동해시 송정동 1683 송정 LH아파트","landNumber":"1683","convX":129.1215666,"dongmyun":"송정동","apartCode":"A24071601","lawdCd":"51170","doroJuso":"강원특별자치도 동해시 동해역길 19"},{"apartName":"아름다운아침","zipCode":"25805","convY":37.4874986,"address":"강원특별자치도 동해시 쇄운동 1100 아름다운아침","landNumber":"1100","convX":129.0990217,"dongmyun":"쇄운동","apartCode":"A24071801","lawdCd":"51170","doroJuso":"강원특별자치도 동해시 효자로 572-1"},{"apartName":"동해석미모닝파크","zipCode":"25805","convY":37.4884343,"address":"강원특별자치도 동해시 쇄운동 1099 동해석미모닝파크","landNumber":"1099","convX":129.1000794,"dongmyun":"쇄운동","apartCode":"A24071802","lawdCd":"51170","doroJuso":"강원특별자치도 동해시 효자로 586"},{"apartName":"발한삼성","zipCode":"25723","convY":37.5535077,"address":"강원특별자치도 동해시 발한동 334-1 발한삼성아파트","landNumber":"334-1","convX":129.1033149,"dongmyun":"발한동","apartCode":"A24080401","lawdCd":"51170","doroJuso":"강원특별자치도 동해시 해안로 605"},{"apartName":"천곡롯데아파트","zipCode":"25781","convY":37.5138092,"address":"강원특별자치도 동해시 천곡동 91-2 롯데아파트","landNumber":"91-2","convX":129.1208562,"dongmyun":"천곡동","apartCode":"A24080701","lawdCd":"51170","doroJuso":"강원특별자치도 동해시 감추7길 22-11"},{"apartName":"천곡현대아파트","zipCode":"25773","convY":37.5189732,"address":"강원특별자치도 동해시 천곡동 380-2 현대아파트","landNumber":"380-2","convX":129.10555,"dongmyun":"천곡동","apartCode":"A24080810","lawdCd":"51170","doroJuso":"강원특별자치도 동해시 한섬로 8"},{"apartName":"천곡주공4차아파트","zipCode":"25765","convY":37.5209209,"address":"강원특별자치도 동해시 천곡동 415 주공4차아파트","landNumber":"415","convX":129.1040294,"dongmyun":"천곡동","apartCode":"A24080812","lawdCd":"51170","doroJuso":"강원특별자치도 동해시 샘실1길 5"},{"apartName":"센트로빌아파트","zipCode":"25767","convY":37.5205624,"address":"강원특별자치도 동해시 천곡동 1060-2 동해 센트로빌 아파트","landNumber":"1060-2","convX":129.1121162,"dongmyun":"천곡동","apartCode":"A24080905","lawdCd":"51170","doroJuso":"강원특별자치도 동해시 한섬로 73"},{"apartName":"동해금호어울림","zipCode":"25749","convY":37.5277339,"address":"강원특별자치도 동해시 천곡동 1102 동해 금호어울림 아파트","landNumber":"1102","convX":129.1021469,"dongmyun":"천곡동","apartCode":"A24081002","lawdCd":"51170","doroJuso":"강원특별자치도 동해시 평릉길 14"},{"apartName":"천곡주공1차아파트","zipCode":"25763","convY":37.5243062,"address":"강원특별자치도 동해시 천곡동 1080 동해천곡주공1차아파트","landNumber":"1080","convX":129.1074979,"dongmyun":"천곡동","apartCode":"A24081006","lawdCd":"51170","doroJuso":"강원특별자치도 동해시 천곡로 20"},{"apartName":"천곡삼성아파트","zipCode":"25760","convY":37.5228128,"address":"강원특별자치도 동해시 천곡동 1077-1 삼성아파트","landNumber":"1077-1","convX":129.1122426,"dongmyun":"천곡동","apartCode":"A24081007","lawdCd":"51170","doroJuso":"강원특별자치도 동해시 대학로 31"},{"apartName":"천곡6LH아파트","zipCode":"25748","convY":37.5285177,"address":"강원특별자치도 동해시 천곡동 1101 천곡6주공아파트","landNumber":"1101","convX":129.1005385,"dongmyun":"천곡동","apartCode":"A24081009","lawdCd":"51170","doroJuso":"강원특별자치도 동해시 평릉1길 37"},{"apartName":"한양1차아파트","zipCode":"25758","convY":37.5262977,"address":"강원특별자치도 동해시 천곡동 791 한양1차아파트","landNumber":"791","convX":129.1070913,"dongmyun":"천곡동","apartCode":"A24081103","lawdCd":"51170","doroJuso":"강원특별자치도 동해시 천곡로 7"},{"apartName":"한양2.3차아파트","zipCode":"25757","convY":37.5266409,"address":"강원특별자치도 동해시 천곡동 794 한양아파트","landNumber":"794","convX":129.1090223,"dongmyun":"천곡동","apartCode":"A24081111","lawdCd":"51170","doroJuso":"강원특별자치도 동해시 천곡로 15"},{"apartName":"쌍용아파트","zipCode":"25770","convY":37.5198714,"address":"강원특별자치도 동해시 천곡동 942 쌍용아파트","landNumber":"942","convX":129.1201272,"dongmyun":"천곡동","apartCode":"A24081204","lawdCd":"51170","doroJuso":"강원특별자치도 동해시 동굴로 149"},{"apartName":"썬샤인파크아파트","zipCode":"25734","convY":37.5385145,"address":"강원특별자치도 동해시 부곡동 80 썬샤인파크","landNumber":"80","convX":129.1028175,"dongmyun":"부곡동","apartCode":"A24081402","lawdCd":"51170","doroJuso":"강원특별자치도 동해시 임항로 10"},{"apartName":"삼화미성","zipCode":"25736","convY":37.5373449,"address":"강원특별자치도 동해시 부곡동 31-2 삼화미성아파트","landNumber":"31-2","convX":129.1092003,"dongmyun":"부곡동","apartCode":"A24081501","lawdCd":"51170","doroJuso":"강원특별자치도 동해시 부곡4길 10"},{"apartName":"삼본아파트","zipCode":"25710","convY":37.5593432,"address":"강원특별자치도 동해시 묵호진동 1-83 삼본아파트","landNumber":"1-83","convX":129.1150229,"dongmyun":"묵호진동","apartCode":"A24081601","lawdCd":"51170","doroJuso":"강원특별자치도 동해시 해맞이길 231"}]}